demo/__init__.py
demo/manage.py
demo/settings.py
demo/urls.py
demo/example/__init__.py
demo/example/forms.py
demo/example/models.py
demo/example/urls.py
demo/example/views.py
formset_bootstrap/__init__.py
formset_bootstrap/apps.py
formset_bootstrap/static/formset_bootstrap/js/jquery.formset.js
django_formset_bootstrap-1.4.0.dev3.dist-info/LICENSE
django_formset_bootstrap-1.4.0.dev3.dist-info/METADATA
django_formset_bootstrap-1.4.0.dev3.dist-info/WHEEL
django_formset_bootstrap-1.4.0.dev3.dist-info/top_level.txt
django_formset_bootstrap-1.4.0.dev3.dist-info/RECORD
