Metadata-Version: 2.1
Name: django-formset-bootstrap
Version: 1.4.0.dev3
Summary: A jQuery plugin that allows you to dynamically add new forms to a rendered django formset.
Home-page: https://github.com/mbourqui/django-formset-bootstrap/
Author: Marc Bourqui
Author-email: pypi.kemar@bourqui.org
License: BSD License
Download-URL: https://github.com/mbourqui/django-formset-bootstrap/releases/tag/v1.4.0.dev3
Keywords: django formset
Platform: UNKNOWN
Classifier: Development Status :: 4 - Beta
Classifier: Environment :: Web Environment
Classifier: Framework :: Django
Classifier: Framework :: Django :: 1.8
Classifier: Framework :: Django :: 1.9
Classifier: Framework :: Django :: 1.10
Classifier: Framework :: Django :: 1.11
Classifier: Intended Audience :: Developers
Classifier: License :: OSI Approved :: BSD License
Classifier: Operating System :: OS Independent
Classifier: Programming Language :: Python
Classifier: Programming Language :: Python :: 2
Classifier: Programming Language :: Python :: 2.7
Classifier: Programming Language :: Python :: 3
Classifier: Programming Language :: Python :: 3.4
Classifier: Programming Language :: Python :: 3.5
Classifier: Programming Language :: Python :: 3.6
Classifier: Topic :: Internet :: WWW/HTTP
Classifier: Topic :: Internet :: WWW/HTTP :: Dynamic Content
Requires-Dist: Django (>=1.9.13)
